feature_store/README.md
feature_store/__init__.py
feature_store/app.py
feature_store/constants.py
feature_store/init_script.sh
feature_store/requirements.txt
feature_store/utils.py
refractfs-1.0.0.dist-info/METADATA
refractfs-1.0.0.dist-info/WHEEL
refractfs-1.0.0.dist-info/top_level.txt
refractfs-1.0.0.dist-info/RECORD
