Metadata-Version: 2.1
Name: refractfs
Version: 1.0.0
Summary: Feature store recipe
Home-page: UNKNOWN
Author: Amit Boke
License: UNKNOWN
Platform: UNKNOWN
Classifier: Programming Language :: Python :: 3.8
Requires-Python: >=3.8,<3.10
Requires-Dist: feast ==0.34.1
